pyphonixjp/__init__.py
pyphonixjp/common.py
pyphonixjp/conversion_table.py
pyphonixjp/phonix.py
pyphonixjp-1.2.dist-info/LICENSE
pyphonixjp-1.2.dist-info/METADATA
pyphonixjp-1.2.dist-info/WHEEL
pyphonixjp-1.2.dist-info/top_level.txt
pyphonixjp-1.2.dist-info/RECORD
