Metadata-Version: 2.1
Name: pyphonixjp
Version: 1.2
Summary: 英単語をひらがなでの読みに変換する。詳しくはHomepage(Github)をご覧ください。
Author: Nanahuse
License: MIT License
Project-URL: Homepage, https://github.com/Nanahuse/PyPhonixJP
Classifier: License :: OSI Approved :: MIT License
Classifier: Programming Language :: Python :: 3.10
Classifier: Programming Language :: Python :: 3.11
Requires-Python: >=3.10
License-File: LICENSE
